anatome/__init__.py
anatome/_distance.py
anatome/fourier.py
anatome/helper.py
anatome/landscape.py
anatome/similarity.py
anatome/utils.py
ultimate_anatome-0.1.1.dist-info/LICENSE
ultimate_anatome-0.1.1.dist-info/METADATA
ultimate_anatome-0.1.1.dist-info/WHEEL
ultimate_anatome-0.1.1.dist-info/top_level.txt
ultimate_anatome-0.1.1.dist-info/RECORD
