Metadata-Version: 2.1
Name: ultimate-anatome
Version: 0.1.1
Summary: Ἀνατομή (Anatome) is a PyTorch library to analyze representation of neural networks
Home-page: https://github.com/brando90/ultimate-anatome
Author: Brando Miranda
Author-email: brandojazz@gmail.com
License: MIT
Platform: UNKNOWN
Requires-Python: >=3.9.0
Requires-Dist: torch (>=1.9.0)
Requires-Dist: torchvision (>=0.10.0)
Requires-Dist: tqdm
